CHANGELOG.rst
crimson/__init__.py
crimson/cli.py
crimson/fastqc.py
crimson/flagstat.py
crimson/fusioncatcher.py
crimson/picard.py
crimson/star.py
crimson/star_fusion.py
crimson/utils.py
crimson/vep.py
crimson-1.1.1.dist-info/entry_points.txt
crimson-1.1.1.dist-info/LICENSE
crimson-1.1.1.dist-info/WHEEL
crimson-1.1.1.dist-info/METADATA
crimson-1.1.1.dist-info/RECORD
