Metadata-Version: 2.1
Name: crimson
Version: 1.1.1
Summary: Bioinformatics tool outputs converter to JSON or YAML
Home-page: https://github.com/bow/crimson
License: BSD-3-Clause
Keywords: bioinformatics,json,yaml
Author: Wibowo Arindrarto
Author-email: contact@arindrarto.dev
Requires-Python: >=3.8,<4.0
Classifier: Development Status :: 3 - Alpha
Classifier: Environment :: Console
Classifier: Intended Audience :: Developers
Classifier: Intended Audience :: Science/Research
Classifier: License :: OSI Approved :: BSD License
Classifier: Operating System :: Microsoft :: Windows
Classifier: Operating System :: POSIX
Classifier: Programming Language :: Python :: 3
Classifier: Programming Language :: Python :: 3.8
Classifier: Programming Language :: Python :: 3.9
Classifier: Programming Language :: Python :: 3.10
Classifier: Programming Language :: Python :: 3.11
Classifier: Programming Language :: Python :: 3.10
Classifier: Programming Language :: Python :: 3.11
Classifier: Programming Language :: Python :: 3.8
Classifier: Programming Language :: Python :: 3.9
Classifier: Topic :: Software Development :: Libraries
Classifier: Topic :: Utilities
Requires-Dist: PyYAML (>=6.0,<7.0)
Requires-Dist: click (>=8.0,<9.0)
Requires-Dist: single-source (>=0.2.0,<0.3.0)
Requires-Dist: urllib3 (>=1.26.16,<2.0.0)
Project-URL: Repository, https://github.com/bow/crimson
